thrmt/__init__.py
thrmt/aliases.py
thrmt/api.py
thrmt/auxiliary.py
thrmt/core.py
thrmt/gellmann_impl.py
thrmt/impl.py
thrmt/quantum_api.py
thrmt/quantum_impl.py
thrmt/types.py
thrmt-0.0.15.dist-info/licenses/LICENSE
thrmt-0.0.15.dist-info/METADATA
thrmt-0.0.15.dist-info/WHEEL
thrmt-0.0.15.dist-info/top_level.txt
thrmt-0.0.15.dist-info/zip-safe
thrmt-0.0.15.dist-info/RECORD
