Metadata-Version: 2.4
Name: thrmt
Version: 0.0.15
Summary: Torched Random Matrix Theory
Author-email: Emanuele Ballarin <emanuele@ballarin.cc>
License: MIT
Project-URL: Homepage, https://github.com/emaballarin/thrmt
Keywords: Deep Learning,Differentiable Programming,Machine Learning,PyTorch,Random Matrices,Random Matrix Theory
Classifier: Development Status :: 3 - Alpha
Classifier: Topic :: Scientific/Engineering :: Mathematics
Classifier: Environment :: Console
Classifier: Programming Language :: Python :: 3
Classifier: License :: OSI Approved :: MIT License
Requires-Python: >=3.10
License-File: LICENSE
Requires-Dist: torch>=2
Dynamic: license-file
